pickelhaube/__init__.py
pickelhaube/cli.py
pickelhaube-0.1.0.dist-info/LICENSE
pickelhaube-0.1.0.dist-info/METADATA
pickelhaube-0.1.0.dist-info/WHEEL
pickelhaube-0.1.0.dist-info/entry_points.txt
pickelhaube-0.1.0.dist-info/top_level.txt
pickelhaube-0.1.0.dist-info/RECORD
