Metadata-Version: 2.1
Name: pickelhaube
Version: 0.1.0
Summary: Secure Pickling
Author-email: Powertools Technologies <simao.afonso@powertools-tech.com>
License: GNU AFFERO GENERAL PUBLIC LICENSE
Project-URL: Source, https://support.powertools-tech.com/PowertoolsTech/pickelhaube
Project-URL: Issues, https://support.powertools-tech.com/PowertoolsTech/pickelhaube/issues
Classifier: Development Status :: 4 - Beta
Classifier: Programming Language :: Python :: 3 :: Only
Classifier: Programming Language :: Python :: 3.8
Classifier: Intended Audience :: Developers
Classifier: License :: OSI Approved :: GNU Lesser General Public License v3 or later (LGPLv3+)
Requires-Python: >=3.8
License-File: LICENSE
